vsc_dataclasses/__init__.py
vsc_dataclasses/constraints.py
vsc_dataclasses/coverage.py
vsc_dataclasses/decorators.py
vsc_dataclasses/expr.py
vsc_dataclasses/types.py
vsc_dataclasses/impl/__init__.py
vsc_dataclasses/impl/bit_t_meta.py
vsc_dataclasses/impl/composite_val_closure.py
vsc_dataclasses/impl/constraint_decl.py
vsc_dataclasses/impl/constraint_decorator_impl.py
vsc_dataclasses/impl/context.py
vsc_dataclasses/impl/covergroup_decorator_impl.py
vsc_dataclasses/impl/ctor.py
vsc_dataclasses/impl/ctor_scope.py
vsc_dataclasses/impl/enum_info.py
vsc_dataclasses/impl/enum_info_mgr.py
vsc_dataclasses/impl/enum_t.py
vsc_dataclasses/impl/enum_t_meta.py
vsc_dataclasses/impl/expr.py
vsc_dataclasses/impl/extend_randclass_decorator_impl.py
vsc_dataclasses/impl/field_base_impl.py
vsc_dataclasses/impl/field_enum_impl.py
vsc_dataclasses/impl/field_list_object_impl.py
vsc_dataclasses/impl/field_list_scalar_impl.py
vsc_dataclasses/impl/field_ref_impl.py
vsc_dataclasses/impl/field_scalar_impl.py
vsc_dataclasses/impl/int_t_meta.py
vsc_dataclasses/impl/list_t.py
vsc_dataclasses/impl/list_t_meta.py
vsc_dataclasses/impl/list_tt_meta.py
vsc_dataclasses/impl/modelinfo.py
vsc_dataclasses/impl/param_t.py
vsc_dataclasses/impl/param_t_meta.py
vsc_dataclasses/impl/rand_list_t.py
vsc_dataclasses/impl/rand_list_t_meta.py
vsc_dataclasses/impl/rand_state.py
vsc_dataclasses/impl/rand_t.py
vsc_dataclasses/impl/rand_t_meta.py
vsc_dataclasses/impl/randclass_decorator_impl.py
vsc_dataclasses/impl/randclass_impl.py
vsc_dataclasses/impl/randobj_decorator_impl.py
vsc_dataclasses/impl/randobj_impl.py
vsc_dataclasses/impl/sample_meta_t.py
vsc_dataclasses/impl/scalar_t.py
vsc_dataclasses/impl/type_kind_e.py
vsc_dataclasses/impl/type_utils.py
vsc_dataclasses/impl/typeinfo_enum.py
vsc_dataclasses/impl/typeinfo_extend_randclass.py
vsc_dataclasses/impl/typeinfo_field.py
vsc_dataclasses/impl/typeinfo_randclass.py
vsc_dataclasses/impl/typeinfo_ref.py
vsc_dataclasses/impl/typeinfo_scalar.py
pyvsc_dataclasses-0.0.1.8548344824.dist-info/LICENSE
pyvsc_dataclasses-0.0.1.8548344824.dist-info/METADATA
pyvsc_dataclasses-0.0.1.8548344824.dist-info/WHEEL
pyvsc_dataclasses-0.0.1.8548344824.dist-info/top_level.txt
pyvsc_dataclasses-0.0.1.8548344824.dist-info/RECORD
