Metadata-Version: 2.1
Name: pyvsc-dataclasses
Version: 0.0.1.8548344824
Summary: Front-end for capturing Verification Stimulus and Coverage constructs using dataclasses
Home-page: https://github.com/vsc-tools/pyvsc-dataclasses
Author: Matthew Ballance
Author-email: matt.ballance@gmail.com
License: Apache 2.0
Keywords: SystemVerilog,Verilog,RTL
License-File: LICENSE
Requires-Dist: pytypeworks
